setup.py
sdpc/Sdpc.py
sdpc/Sdpc_struct.py
sdpc/__init__.py
sdpcPY.egg-info/PKG-INFO
sdpcPY.egg-info/SOURCES.txt
sdpcPY.egg-info/dependency_links.txt
sdpcPY.egg-info/requires.txt
sdpcPY.egg-info/top_level.txt
sdpc/DLL/DecodeHevc.lib
sdpc/DLL/DecodeSdpcDll.lib
sdpc/DLL/avcodec.lib
sdpc/DLL/avdevice.lib
sdpc/DLL/avfilter.lib
sdpc/DLL/avformat.lib
sdpc/DLL/avutil.lib
sdpc/DLL/postproc.lib
sdpc/DLL/swresample.lib
sdpc/DLL/swscale.lib
sdpc/DLL/turbojpeg-static.lib
sdpc/DLL/dll/DecodeHevc.dll
sdpc/DLL/dll/DecodeSdpcDll.dll
sdpc/DLL/dll/avcodec-58.dll
sdpc/DLL/dll/avdevice-58.dll
sdpc/DLL/dll/avfilter-7.dll
sdpc/DLL/dll/avformat-58.dll
sdpc/DLL/dll/avutil-56.dll
sdpc/DLL/dll/postproc-55.dll
sdpc/DLL/dll/swresample-3.dll
sdpc/DLL/dll/swscale-5.dll
sdpc/so/libDecodeHevc.so
sdpc/so/libDecodeSdpc.so
sdpc/so/ffmpeg/libavcodec.so
sdpc/so/ffmpeg/libavcodec.so.58
sdpc/so/ffmpeg/libavcodec.so.58.111.100
sdpc/so/ffmpeg/libavdevice.so
sdpc/so/ffmpeg/libavdevice.so.58
sdpc/so/ffmpeg/libavdevice.so.58.11.102
sdpc/so/ffmpeg/libavfilter.so
sdpc/so/ffmpeg/libavfilter.so.7
sdpc/so/ffmpeg/libavfilter.so.7.87.100
sdpc/so/ffmpeg/libavformat.so
sdpc/so/ffmpeg/libavformat.so.58
sdpc/so/ffmpeg/libavformat.so.58.62.100
sdpc/so/ffmpeg/libavutil.so
sdpc/so/ffmpeg/libavutil.so.56
sdpc/so/ffmpeg/libavutil.so.56.60.100
sdpc/so/ffmpeg/libswresample.so
sdpc/so/ffmpeg/libswresample.so.3
sdpc/so/ffmpeg/libswresample.so.3.8.100
sdpc/so/ffmpeg/libswscale.so
sdpc/so/ffmpeg/libswscale.so.5
sdpc/so/ffmpeg/libswscale.so.5.8.100
sdpc/so/ffmpeg/libx264.so
sdpc/so/ffmpeg/libx264.so.148
sdpc/so/ffmpeg/libx265.so
sdpc/so/ffmpeg/libx265.so.79
sdpc/so/jpeg/libjpeg.a
sdpc/so/jpeg/libjpeg.so
sdpc/so/jpeg/libjpeg.so.8
sdpc/so/jpeg/libjpeg.so.8.2.2
sdpc/so/jpeg/libturbojpeg.a
sdpc/so/jpeg/libturbojpeg.so
sdpc/so/jpeg/libturbojpeg.so.0
sdpc/so/jpeg/libturbojpeg.so.0.2.0