Metadata-Version: 1.0
Name: sdpcPY
Version: 1.4
Summary: a library for sdpcPY (linux version)
Home-page: UNKNOWN
Author: Jiawen Li
Author-email: lijiawen21@mails.tsinghua.edu.cn
License: MIT License
Platform: linux
